k8ctl/__init__.py
k8ctl/helper.py
k8ctl/k8ctl.py
k8ctl-0.0.11.dist-info/LICENSE
k8ctl-0.0.11.dist-info/METADATA
k8ctl-0.0.11.dist-info/WHEEL
k8ctl-0.0.11.dist-info/entry_points.txt
k8ctl-0.0.11.dist-info/top_level.txt
k8ctl-0.0.11.dist-info/RECORD
