Metadata-Version: 2.1
Name: k8ctl
Version: 0.0.11
Author: Kishorekarthik P
License-File: LICENSE
Requires-Dist: click
